csvtoexcel/csvtoexcel.py
csvtoexcel/exceltocsv.py
csvtoexcel-0.1.2.dist-info/entry_points.txt
csvtoexcel-0.1.2.dist-info/WHEEL
csvtoexcel-0.1.2.dist-info/METADATA
csvtoexcel-0.1.2.dist-info/RECORD
